Topsis-Tanya-102016109/__init__.py
Topsis-Tanya-102016109/topsis.py
Topsis_Tanya/__init__.py
Topsis_Tanya/topsis.py
Topsis_Tanya_102016109-0.1.dist-info/LICENSE.txt
Topsis_Tanya_102016109-0.1.dist-info/METADATA
Topsis_Tanya_102016109-0.1.dist-info/WHEEL
Topsis_Tanya_102016109-0.1.dist-info/top_level.txt
Topsis_Tanya_102016109-0.1.dist-info/RECORD
