Metadata-Version: 2.1
Name: Topsis-Tanya-102016109
Version: 0.1
Summary: Topsis
Author: Tanya
Author-email: tgarg1_be20@thapar.edu
Classifier: Programming Language :: Python :: 3
Classifier: License :: OSI Approved :: MIT License
Classifier: Operating System :: OS Independent
License-File: LICENSE.txt
